m_demo/__init__.py
m_demo/test.py
m_demo/test_2.py
m_demo-0.1.2.dist-info/LICENSE
m_demo-0.1.2.dist-info/WHEEL
m_demo-0.1.2.dist-info/METADATA
m_demo-0.1.2.dist-info/RECORD
