Metadata-Version: 2.3
Name: m_demo
Version: 0.1.2
Summary: Just a test for using Flit
Author-email: "Exneyder A. Montoya-Araque" <eamontoyaa@gmail.com>, Second Author Test <2nd_author_test@email.com>
Requires-Python: >=3.6
Requires-Dist: numpy >=1.22.4
Requires-Dist: matplotlib >=3.5.2
Requires-Dist: scipy >= 1.9.0
